lmflow/__init__.py
lmflow-0.0.1.dev0.dist-info/METADATA
lmflow-0.0.1.dev0.dist-info/WHEEL
lmflow-0.0.1.dev0.dist-info/top_level.txt
lmflow-0.0.1.dev0.dist-info/RECORD
