Metadata-Version: 2.1
Name: lmflow
Version: 0.0.1.dev0
Summary: lmflow - An Extensible Toolkit for Finetuning and Inference of Large Foundation Models
Author: Shadow Walker
License: UNKNOWN
Keywords: lmflow
Platform: UNKNOWN
Classifier: Programming Language :: Python :: 3
Classifier: Programming Language :: Python :: 3.8
Classifier: Programming Language :: Python :: 3.9
Classifier: Programming Language :: Python :: 3.10
Requires-Dist: torch
